bobtail_logger/__init__.py
bobtail_logger/logger.py
bobtail_logger-0.0.1.dist-info/LICENSE
bobtail_logger-0.0.1.dist-info/METADATA
bobtail_logger-0.0.1.dist-info/WHEEL
bobtail_logger-0.0.1.dist-info/top_level.txt
bobtail_logger-0.0.1.dist-info/RECORD
